the_worst_queue/__init__.py
the_worst_queue-0.0.1.dev0.dist-info/LICENSE
the_worst_queue-0.0.1.dev0.dist-info/METADATA
the_worst_queue-0.0.1.dev0.dist-info/WHEEL
the_worst_queue-0.0.1.dev0.dist-info/RECORD
