Metadata-Version: 2.1
Name: the-worst-queue
Version: 0.0.1.dev0
Summary: A simple jobs queue built with "worse is better" in mind.
License: MIT
Author: weihong.xu
Author-email: xuweihong.cn@gmail.com
Requires-Python: >=3.8,<4.0
Classifier: License :: OSI Approved :: MIT License
Classifier: Programming Language :: Python :: 3
Classifier: Programming Language :: Python :: 3.8
Classifier: Programming Language :: Python :: 3.9
Classifier: Programming Language :: Python :: 3.10
Classifier: Programming Language :: Python :: 3.11
Classifier: Programming Language :: Python :: 3.12
